monkeytype/__init__.py
monkeytype/__main__.py
monkeytype/cli.py
monkeytype/compat.py
monkeytype/config.py
monkeytype/encoding.py
monkeytype/exceptions.py
monkeytype/py.typed
monkeytype/stubs.py
monkeytype/tracing.py
monkeytype/type_checking_imports_transformer.py
monkeytype/typing.py
monkeytype/util.py
monkeytype/db/__init__.py
monkeytype/db/base.py
monkeytype/db/sqlite.py
MonkeyType-23.3.0.dist-info/LICENSE
MonkeyType-23.3.0.dist-info/METADATA
MonkeyType-23.3.0.dist-info/WHEEL
MonkeyType-23.3.0.dist-info/entry_points.txt
MonkeyType-23.3.0.dist-info/top_level.txt
MonkeyType-23.3.0.dist-info/RECORD
