Metadata-Version: 2.1
Name: MonkeyType
Version: 23.3.0
Summary: Generating type annotations from sampled production types
Home-page: https://github.com/Instagram/MonkeyType
Author: Matt Page
Author-email: mpage@instagram.com
License: BSD
Classifier: Development Status :: 5 - Production/Stable
Classifier: Intended Audience :: Developers
Classifier: License :: OSI Approved :: BSD License
Classifier: Operating System :: OS Independent
Classifier: Programming Language :: Python
Classifier: Programming Language :: Python :: 3
Classifier: Programming Language :: Python :: 3.7
Classifier: Programming Language :: Python :: 3.8
Classifier: Programming Language :: Python :: 3.9
Classifier: Programming Language :: Python :: 3.10
Requires-Python: >=3.7
Provides-Extra: dev
License-File: LICENSE
